{
 "ExecutionDate": "2021-08-21T00:33:15Z",
 "DataDays": 7,
 "Source": "kubevirt/hyperconverged-cluster-operator",
 "Data": {
  "AverageMergeQueueLength": {
   "Avg": 0.14,
   "Std": 0.35,
   "DataPoints": [
    {
     "Value": 1,
     "Date": "2021-08-21T00:33:15.80840295Z",
     "PRs": [
      1490
     ]
    },
    {
     "Value": 0,
     "Date": "2021-08-20T00:33:15.80840295Z"
    },
    {
     "Value": 0,
     "Date": "2021-08-19T00:33:15.80840295Z"
    },
    {
     "Value": 0,
     "Date": "2021-08-18T00:33:15.80840295Z"
    },
    {
     "Value": 0,
     "Date": "2021-08-17T00:33:15.80840295Z"
    },
    {
     "Value": 0,
     "Date": "2021-08-16T00:33:15.80840295Z"
    },
    {
     "Value": 0,
     "Date": "2021-08-15T00:33:15.80840295Z"
    }
   ]
  },
  "AverageRetestsToMerge": {
   "Avg": 1.7,
   "Std": 1.9,
   "DataPoints": [
    {
     "Value": 0,
     "PRs": [
      1486
     ]
    },
    {
     "Value": 0,
     "PRs": [
      1485
     ]
    },
    {
     "Value": 1,
     "PRs": [
      1482
     ]
    },
    {
     "Value": 1,
     "PRs": [
      1480
     ]
    },
    {
     "Value": 5,
     "PRs": [
      1476
     ]
    },
    {
     "Value": 0,
     "PRs": [
      1488
     ]
    },
    {
     "Value": 5,
     "PRs": [
      1487
     ]
    },
    {
     "Value": 2,
     "PRs": [
      1475
     ]
    },
    {
     "Value": 0,
     "PRs": [
      1492
     ]
    },
    {
     "Value": 3,
     "PRs": [
      1484
     ]
    }
   ]
  },
  "AverageTimeToMerge": {
   "Avg": 0.14,
   "Std": 0.1,
   "DataPoints": [
    {
     "Value": 0.07,
     "PRs": [
      1475
     ]
    },
    {
     "Value": 0.13,
     "PRs": [
      1488
     ]
    },
    {
     "Value": 0.13,
     "PRs": [
      1486
     ]
    },
    {
     "Value": 0.07,
     "PRs": [
      1485
     ]
    },
    {
     "Value": 0.31,
     "PRs": [
      1484
     ]
    },
    {
     "Value": 0.14,
     "PRs": [
      1482
     ]
    },
    {
     "Value": 0,
     "PRs": [
      1480
     ]
    },
    {
     "Value": 0.28,
     "PRs": [
      1476
     ]
    }
   ]
  }
 }
}