{
 "ExecutionDate": "2022-01-12T09:12:26Z",
 "DataDays": 7,
 "Source": "kubevirt/hyperconverged-cluster-operator",
 "Data": {
  "AverageMergeQueueLength": {
   "Avg": 0.86,
   "Std": 0.35,
   "DataPoints": [
    {
     "Value": 0,
     "Date": "2022-01-12T09:12:26.613049693Z"
    },
    {
     "Value": 1,
     "Date": "2022-01-11T09:12:26.613049693Z",
     "PRs": [
      1687
     ]
    },
    {
     "Value": 1,
     "Date": "2022-01-10T09:12:26.613049693Z",
     "PRs": [
      1687
     ]
    },
    {
     "Value": 1,
     "Date": "2022-01-09T09:12:26.613049693Z",
     "PRs": [
      1687
     ]
    },
    {
     "Value": 1,
     "Date": "2022-01-08T09:12:26.613049693Z",
     "PRs": [
      1687
     ]
    },
    {
     "Value": 1,
     "Date": "2022-01-07T09:12:26.613049693Z",
     "PRs": [
      1687
     ]
    },
    {
     "Value": 1,
     "Date": "2022-01-06T09:12:26.613049693Z",
     "PRs": [
      1684
     ]
    }
   ]
  },
  "AverageRetestsToMerge": {
   "Avg": 2.5,
   "Std": 3.25,
   "DataPoints": [
    {
     "Value": 6,
     "PRs": [
      1697
     ]
    },
    {
     "Value": 0,
     "PRs": [
      1696
     ]
    },
    {
     "Value": 0,
     "PRs": [
      1690
     ]
    },
    {
     "Value": 8,
     "PRs": [
      1684
     ]
    },
    {
     "Value": 1,
     "PRs": [
      1680
     ]
    },
    {
     "Value": 0,
     "PRs": [
      1698
     ]
    }
   ]
  },
  "AverageTimeToMerge": {
   "Avg": 0.29,
   "Std": 0.44,
   "DataPoints": [
    {
     "Value": 0,
     "PRs": [
      1696
     ]
    },
    {
     "Value": 0,
     "PRs": [
      1690
     ]
    },
    {
     "Value": 1.16,
     "PRs": [
      1684
     ]
    },
    {
     "Value": 0.56,
     "PRs": [
      1680
     ]
    },
    {
     "Value": 0,
     "PRs": [
      1698
     ]
    },
    {
     "Value": 0,
     "PRs": [
      1697
     ]
    }
   ]
  }
 }
}